aceparse/__init__.py
aceparse/_version.py
aceparse/ace_argparser.py
aceparse/extensions.py
aceparse/extensions.pyi
aceparse/py311.py
aceparse-0.2.2.dist-info/licenses/LICENSE
aceparse-0.2.2.dist-info/METADATA
aceparse-0.2.2.dist-info/WHEEL
aceparse-0.2.2.dist-info/top_level.txt
aceparse-0.2.2.dist-info/RECORD
