Metadata-Version: 2.4
Name: aceparse
Version: 0.2.2
Summary: Improved argparse.ArgumentParser that works with dataclasses
Requires-Python: >=3.10
License-File: LICENSE
Requires-Dist: pyyaml>=6.0.2
Provides-Extra: test
Requires-Dist: flake8; extra == "test"
Requires-Dist: hatch; extra == "test"
Requires-Dist: pydantic>=2.10.4; extra == "test"
Requires-Dist: pytest; extra == "test"
Dynamic: license-file
